ohc_backend/__init__.py
ohc_backend/__main__.py
ohc_backend/dependencies.py
ohc_backend/errors.py
ohc_backend/main.py
ohc_backend/models/__init__.py
ohc_backend/models/ha_entity.py
ohc_backend/routers/__init__.py
ohc_backend/routers/automations.py
ohc_backend/routers/github.py
ohc_backend/services/__init__.py
ohc_backend/services/ha_service.py
ohc_backend/services/ohc_state.py
ohc_backend/services/settings.py
ohc_backend/services/sync_manager.py
ohc_backend/services/github/__init__.py
ohc_backend/services/github/auth.py
ohc_backend/services/github/base.py
ohc_backend/services/github/client.py
ohc_backend/services/github/content.py
ohc_backend/services/github/errors.py
ohc_backend/services/github/models.py
ohc_backend/services/github/repository.py
ohc_backend/services/github/rest.py
ohc_backend/services/github/templates/README.md
ohc_backend/utils/logging.py
ohc_backend/utils/request_context.py
ohc_backend-1.2.6.dist-info/METADATA
ohc_backend-1.2.6.dist-info/WHEEL
ohc_backend-1.2.6.dist-info/licenses/LICENSE
ohc_backend-1.2.6.dist-info/RECORD
