Metadata-Version: 2.4
Name: OHC_Backend
Version: 1.2.6
Summary: Add your description here
License-File: LICENSE
Requires-Python: >=3.13
Requires-Dist: aiofiles>=24.1.0
Requires-Dist: aiohttp>=3.11.12
Requires-Dist: fastapi[standard]>=0.115.8
Requires-Dist: uvicorn>=0.34.0
